Workbook
Name Price: '前提入力'!$B$3
Name DownPayment: '前提入力'!$B$4
Name LoanAmount: '前提入力'!$B$5
Name InterestRate: '前提入力'!$B$6
Name LoanYears: '前提入力'!$B$7
Name BonusFlag: '前提入力'!$B$8
Name BonusAmount: '前提入力'!$B$9
Name PurchaseCost: '前提入力'!$B$10
Name MgmtFee: '前提入力'!$B$11
Name ReserveFee: '前提入力'!$B$12
Name ParkingFee: '前提入力'!$B$13
Name PropertyTax: '前提入力'!$B$14
Name FireInsurance: '前提入力'!$B$15
Name OtherMaintenance: '前提入力'!$B$16
Name LoanDeduction: '前提入力'!$B$17
Name HoldYears: '前提入力'!$B$18
Name SalePrice: '前提入力'!$B$19
Name SaleFeeRate: '前提入力'!$B$20
Name SaleOtherCost: '前提入力'!$B$21
Name MovingCost: '前提入力'!$B$22
Name CurrentRent: '前提入力'!$B$23

Sheet 前提入力
A1: 前提入力（パラメータ設定シート）
A2: 項目 | B2: 値 | C2: 単位 | D2: 説明
A3: 物件価格 | B3: 50000000 | C3: 円 | D3: 購入する住宅の価格
A4: 頭金 | B4: 5000000 | C4: 円 | D4: 購入時に現金で支払う頭金
A5: 借入額 | B5: =B3-B4 | C5: 円 | D5: 原則「物件価格-頭金」で自動計算。必要なら直接金額を上書き入力可
A6: ローン金利（年率） | B6: 0.007 | C6: % | D6: 住宅ローンの年利（変動・固定の代表値）
A7: 返済期間 | B7: 35 | C7: 年 | D7: ローンの返済期間
A8: ボーナス返済の有無 | B8: なし | C8: - | D8: "あり"または"なし"を選択
A9: ボーナス返済額（1回あたり） | B9: 100000 | C9: 円 | D9: ボーナス返済を行う月（6か月・12か月目等）に上乗せする金額
A10: 購入時諸費用 | B10: 2000000 | C10: 円 | D10: 仲介手数料・登記費用・ローン手数料等の購入時費用合計
A11: 管理費（月額） | B11: 15000 | C11: 円 | D11: マンション管理費等（戸建ては0でよい）
A12: 修繕積立金（月額） | B12: 10000 | C12: 円 | D12: 修繕積立金（戸建ては想定額を入力）
A13: 駐車場代（月額） | B13: 0 | C13: 円 | D13: 駐車場を別途契約する場合の月額
A14: 固定資産税（年額） | B14: 150000 | C14: 円 | D14: 固定資産税・都市計画税の年額目安
A15: 火災保険料（年額） | B15: 20000 | C15: 円 | D15: 火災保険・地震保険の年額
A16: その他維持費（年額） | B16: 30000 | C16: 円 | D16: リフォーム・設備更新等の積立目安
A17: 住宅ローン控除額（年額） | B17: 200000 | C17: 円 | D17: 簡易計算：控除を受けられる年に一律で適用する金額
A18: 保有年数 | B18: 10 | C18: 年 | D18: 購入後、売却までの保有年数
A19: 売却予定価格 | B19: 45000000 | C19: 円 | D19: 保有年数後に売却できると想定する価格
A20: 売却時仲介手数料率 | B20: 0.03 | C20: % | D20: 売却時に仲介会社へ支払う手数料の率（目安3%+消費税相当含む簡易値）
... A23: 賃貸比較用の現在家賃（月額） | B23: 120000 | C23: 円 | D23: 購入せず賃貸を続けた場合に支払うであろう月額家賃

Sheet ローン返済表
A1: ローン返済表（月次）
A2: 月数 | B2: 年数 | C2: 期首ローン残高 | D2: 月返済額 | E2: 利息 | F2: 元本返済額 | G2: ボーナス返済額 | H2: 期末ローン残高 | I2: 累計返済額 | J2: 累計利息 | K2: 累計元本返済額
A3: 1 | B3: =INT((A3-1)/12)+1 | C3: =LoanAmount | D3: =IF(C3<=0,0,MIN(-PMT(InterestRate/12,LoanYears*12,LoanAmount),C3+E3)) | E3: =IF(C3>0,C3*InterestRate/12,0) | F3: =D3-E3 | G3: =IF(AND(BonusFlag="あり",MOD(A3,6)=0,C3-F3>0),MIN(BonusAmount,C3-F3),0) | H3: =MAX(C3-F3-G3,0) | I3: =D3+G3 | J3: =E3 | K3: =F3+G3
A4: 2 | B4: =INT((A4-1)/12)+1 | C4: =H3 | D4: =IF(C4<=0,0,MIN(-PMT(InterestRate/12,LoanYears*12,LoanAmount),C4+E4)) | E4: =IF(C4>0,C4*InterestRate/12,0) | F4: =D4-E4 | G4: =IF(AND(BonusFlag="あり",MOD(A4,6)=0,C4-F4>0),MIN(BonusAmount,C4-F4),0) | H4: =MAX(C4-F4-G4,0) | I4: =I3+D4+G4 | J4: =J3+E4 | K4: =K3+F4+G4
A5: 3 | B5: =INT((A5-1)/12)+1 | C5: =H4 | D5: =IF(C5<=0,0,MIN(-PMT(InterestRate/12,LoanYears*12,LoanAmount),C5+E5)) | E5: =IF(C5>0,C5*InterestRate/12,0) | F5: =D5-E5 | G5: =IF(AND(BonusFlag="あり",MOD(A5,6)=0,C5-F5>0),MIN(BonusAmount,C5-F5),0) | H5: =MAX(C5-F5-G5,0) | I5: =I4+D5+G5 | J5: =J4+E5 | K5: =K4+F5+G5
A6: 4 | B6: =INT((A6-1)/12)+1 | C6: =H5 | D6: =IF(C6<=0,0,MIN(-PMT(InterestRate/12,LoanYears*12,LoanAmount),C6+E6)) | E6: =IF(C6>0,C6*InterestRate/12,0) | F6: =D6-E6 | G6: =IF(AND(BonusFlag="あり",MOD(A6,6)=0,C6-F6>0),MIN(BonusAmount,C6-F6),0) | H6: =MAX(C6-F6-G6,0) | I6: =I5+D6+G6 | J6: =J5+E6 | K6: =K5+F6+G6
A7: 5 | B7: =INT((A7-1)/12)+1 | C7: =H6 | D7: =IF(C7<=0,0,MIN(-PMT(InterestRate/12,LoanYears*12,LoanAmount),C7+E7)) | E7: =IF(C7>0,C7*InterestRate/12,0) | F7: =D7-E7 | G7: =IF(AND(BonusFlag="あり",MOD(A7,6)=0,C7-F7>0),MIN(BonusAmount,C7-F7),0) | H7: =MAX(C7-F7-G7,0) | I7: =I6+D7+G7 | J7: =J6+E7 | K7: =K6+F7+G7
A8: 6 | B8: =INT((A8-1)/12)+1 | C8: =H7 | D8: =IF(C8<=0,0,MIN(-PMT(InterestRate/12,LoanYears*12,LoanAmount),C8+E8)) | E8: =IF(C8>0,C8*InterestRate/12,0) | F8: =D8-E8 | G8: =IF(AND(BonusFlag="あり",MOD(A8,6)=0,C8-F8>0),MIN(BonusAmount,C8-F8),0) | H8: =MAX(C8-F8-G8,0) | I8: =I7+D8+G8 | J8: =J7+E8 | K8: =K7+F8+G8
A9: 7 | B9: =INT((A9-1)/12)+1 | C9: =H8 | D9: =IF(C9<=0,0,MIN(-PMT(InterestRate/12,LoanYears*12,LoanAmount),C9+E9)) | E9: =IF(C9>0,C9*InterestRate/12,0) | F9: =D9-E9 | G9: =IF(AND(BonusFlag="あり",MOD(A9,6)=0,C9-F9>0),MIN(BonusAmount,C9-F9),0) | H9: =MAX(C9-F9-G9,0) | I9: =I8+D9+G9 | J9: =J8+E9 | K9: =K8+F9+G9
A10: 8 | B10: =INT((A10-1)/12)+1 | C10: =H9 | D10: =IF(C10<=0,0,MIN(-PMT(InterestRate/12,LoanYears*12,LoanAmount),C10+E10)) | E10: =IF(C10>0,C10*InterestRate/12,0) | F10: =D10-E10 | G10: =IF(AND(BonusFlag="あり",MOD(A10,6)=0,C10-F10>0),MIN(BonusAmount,C10-F10),0) | H10: =MAX(C10-F10-G10,0) | I10: =I9+D10+G10 | J10: =J9+E10 | K10: =K9+F10+G10
A11: 9 | B11: =INT((A11-1)/12)+1 | C11: =H10 | D11: =IF(C11<=0,0,MIN(-PMT(InterestRate/12,LoanYears*12,LoanAmount),C11+E11)) | E11: =IF(C11>0,C11*InterestRate/12,0) | F11: =D11-E11 | G11: =IF(AND(BonusFlag="あり",MOD(A11,6)=0,C11-F11>0),MIN(BonusAmount,C11-F11),0) | H11: =MAX(C11-F11-G11,0) | I11: =I10+D11+G11 | J11: =J10+E11 | K11: =K10+F11+G11
A12: 10 | B12: =INT((A12-1)/12)+1 | C12: =H11 | D12: =IF(C12<=0,0,MIN(-PMT(InterestRate/12,LoanYears*12,LoanAmount),C12+E12)) | E12: =IF(C12>0,C12*InterestRate/12,0) | F12: =D12-E12 | G12: =IF(AND(BonusFlag="あり",MOD(A12,6)=0,C12-F12>0),MIN(BonusAmount,C12-F12),0) | H12: =MAX(C12-F12-G12,0) | I12: =I11+D12+G12 | J12: =J11+E12 | K12: =K11+F12+G12
A13: 11 | B13: =INT((A13-1)/12)+1 | C13: =H12 | D13: =IF(C13<=0,0,MIN(-PMT(InterestRate/12,LoanYears*12,LoanAmount),C13+E13)) | E13: =IF(C13>0,C13*InterestRate/12,0) | F13: =D13-E13 | G13: =IF(AND(BonusFlag="あり",MOD(A13,6)=0,C13-F13>0),MIN(BonusAmount,C13-F13),0) | H13: =MAX(C13-F13-G13,0) | I13: =I12+D13+G13 | J13: =J12+E13 | K13: =K12+F13+G13
A14: 12 | B14: =INT((A14-1)/12)+1 | C14: =H13 | D14: =IF(C14<=0,0,MIN(-PMT(InterestRate/12,LoanYears*12,LoanAmount),C14+E14)) | E14: =IF(C14>0,C14*InterestRate/12,0) | F14: =D14-E14 | G14: =IF(AND(BonusFlag="あり",MOD(A14,6)=0,C14-F14>0),MIN(BonusAmount,C14-F14),0) | H14: =MAX(C14-F14-G14,0) | I14: =I13+D14+G14 | J14: =J13+E14 | K14: =K13+F14+G14
A15: 13 | B15: =INT((A15-1)/12)+1 | C15: =H14 | D15: =IF(C15<=0,0,MIN(-PMT(InterestRate/12,LoanYears*12,LoanAmount),C15+E15)) | E15: =IF(C15>0,C15*InterestRate/12,0) | F15: =D15-E15 | G15: =IF(AND(BonusFlag="あり",MOD(A15,6)=0,C15-F15>0),MIN(BonusAmount,C15-F15),0) | H15: =MAX(C15-F15-G15,0) | I15: =I14+D15+G15 | J15: =J14+E15 | K15: =K14+F15+G15
... A422: 420 | B422: =INT((A422-1)/12)+1 | C422: =H421 | D422: =IF(C422<=0,0,MIN(-PMT(InterestRate/12,LoanYears*12,LoanAmount),C422+E422)) | E422: =IF(C422>0,C422*InterestRate/12,0) | F422: =D422-E422 | G422: =IF(AND(BonusFlag="あり",MOD(A422,6)=0,C422-F422>0),MIN(BonusAmount,C422-F422),0) | H422: =MAX(C422-F422-G422,0) | I422: =I421+D422+G422 | J422: =J421+E422 | K422: =K421+F422+G422

Sheet 年次集計
A1: 年次集計（年単位の支出まとめ）
A2: 年 | B2: ローン返済額 | C2: うち利息 | D2: うち元本返済 | E2: 管理費 | F2: 修繕積立金 | G2: 駐車場代 | H2: 固定資産税 | I2: 火災保険料 | J2: その他維持費 | K2: 住宅ローン控除 | L2: 年間実質支出 | M2: 累計実質支出 | N2: 年末ローン残高
A3: 1 | B3: =SUMIFS(ローン返済表!D:D,ローン返済表!B:B,A3)+SUMIFS(ローン返済表!G:G,ローン返済表!B:B,A3) | C3: =SUMIFS(ローン返済表!E:E,ローン返済表!B:B,A3) | D3: =SUMIFS(ローン返済表!F:F,ローン返済表!B:B,A3)+SUMIFS(ローン返済表!G:G,ローン返済表!B:B,A3) | E3: =MgmtFee*12 | F3: =ReserveFee*12 | G3: =ParkingFee*12 | H3: =PropertyTax | I3: =FireInsurance | J3: =OtherMaintenance | K3: =IF(A3<=LoanYears,LoanDeduction,0) | L3: =B3+E3+F3+G3+H3+I3+J3-K3 | M3: =L3 | N3: =INDEX(ローン返済表!H:H,A3*12+1)
A4: 2 | B4: =SUMIFS(ローン返済表!D:D,ローン返済表!B:B,A4)+SUMIFS(ローン返済表!G:G,ローン返済表!B:B,A4) | C4: =SUMIFS(ローン返済表!E:E,ローン返済表!B:B,A4) | D4: =SUMIFS(ローン返済表!F:F,ローン返済表!B:B,A4)+SUMIFS(ローン返済表!G:G,ローン返済表!B:B,A4) | E4: =MgmtFee*12 | F4: =ReserveFee*12 | G4: =ParkingFee*12 | H4: =PropertyTax | I4: =FireInsurance | J4: =OtherMaintenance | K4: =IF(A4<=LoanYears,LoanDeduction,0) | L4: =B4+E4+F4+G4+H4+I4+J4-K4 | M4: =M3+L4 | N4: =INDEX(ローン返済表!H:H,A4*12+1)
A5: 3 | B5: =SUMIFS(ローン返済表!D:D,ローン返済表!B:B,A5)+SUMIFS(ローン返済表!G:G,ローン返済表!B:B,A5) | C5: =SUMIFS(ローン返済表!E:E,ローン返済表!B:B,A5) | D5: =SUMIFS(ローン返済表!F:F,ローン返済表!B:B,A5)+SUMIFS(ローン返済表!G:G,ローン返済表!B:B,A5) | E5: =MgmtFee*12 | F5: =ReserveFee*12 | G5: =ParkingFee*12 | H5: =PropertyTax | I5: =FireInsurance | J5: =OtherMaintenance | K5: =IF(A5<=LoanYears,LoanDeduction,0) | L5: =B5+E5+F5+G5+H5+I5+J5-K5 | M5: =M4+L5 | N5: =INDEX(ローン返済表!H:H,A5*12+1)
A6: 4 | B6: =SUMIFS(ローン返済表!D:D,ローン返済表!B:B,A6)+SUMIFS(ローン返済表!G:G,ローン返済表!B:B,A6) | C6: =SUMIFS(ローン返済表!E:E,ローン返済表!B:B,A6) | D6: =SUMIFS(ローン返済表!F:F,ローン返済表!B:B,A6)+SUMIFS(ローン返済表!G:G,ローン返済表!B:B,A6) | E6: =MgmtFee*12 | F6: =ReserveFee*12 | G6: =ParkingFee*12 | H6: =PropertyTax | I6: =FireInsurance | J6: =OtherMaintenance | K6: =IF(A6<=LoanYears,LoanDeduction,0) | L6: =B6+E6+F6+G6+H6+I6+J6-K6 | M6: =M5+L6 | N6: =INDEX(ローン返済表!H:H,A6*12+1)
A7: 5 | B7: =SUMIFS(ローン返済表!D:D,ローン返済表!B:B,A7)+SUMIFS(ローン返済表!G:G,ローン返済表!B:B,A7) | C7: =SUMIFS(ローン返済表!E:E,ローン返済表!B:B,A7) | D7: =SUMIFS(ローン返済表!F:F,ローン返済表!B:B,A7)+SUMIFS(ローン返済表!G:G,ローン返済表!B:B,A7) | E7: =MgmtFee*12 | F7: =ReserveFee*12 | G7: =ParkingFee*12 | H7: =PropertyTax | I7: =FireInsurance | J7: =OtherMaintenance | K7: =IF(A7<=LoanYears,LoanDeduction,0) | L7: =B7+E7+F7+G7+H7+I7+J7-K7 | M7: =M6+L7 | N7: =INDEX(ローン返済表!H:H,A7*12+1)
A8: 6 | B8: =SUMIFS(ローン返済表!D:D,ローン返済表!B:B,A8)+SUMIFS(ローン返済表!G:G,ローン返済表!B:B,A8) | C8: =SUMIFS(ローン返済表!E:E,ローン返済表!B:B,A8) | D8: =SUMIFS(ローン返済表!F:F,ローン返済表!B:B,A8)+SUMIFS(ローン返済表!G:G,ローン返済表!B:B,A8) | E8: =MgmtFee*12 | F8: =ReserveFee*12 | G8: =ParkingFee*12 | H8: =PropertyTax | I8: =FireInsurance | J8: =OtherMaintenance | K8: =IF(A8<=LoanYears,LoanDeduction,0) | L8: =B8+E8+F8+G8+H8+I8+J8-K8 | M8: =M7+L8 | N8: =INDEX(ローン返済表!H:H,A8*12+1)
A9: 7 | B9: =SUMIFS(ローン返済表!D:D,ローン返済表!B:B,A9)+SUMIFS(ローン返済表!G:G,ローン返済表!B:B,A9) | C9: =SUMIFS(ローン返済表!E:E,ローン返済表!B:B,A9) | D9: =SUMIFS(ローン返済表!F:F,ローン返済表!B:B,A9)+SUMIFS(ローン返済表!G:G,ローン返済表!B:B,A9) | E9: =MgmtFee*12 | F9: =ReserveFee*12 | G9: =ParkingFee*12 | H9: =PropertyTax | I9: =FireInsurance | J9: =OtherMaintenance | K9: =IF(A9<=LoanYears,LoanDeduction,0) | L9: =B9+E9+F9+G9+H9+I9+J9-K9 | M9: =M8+L9 | N9: =INDEX(ローン返済表!H:H,A9*12+1)
A10: 8 | B10: =SUMIFS(ローン返済表!D:D,ローン返済表!B:B,A10)+SUMIFS(ローン返済表!G:G,ローン返済表!B:B,A10) | C10: =SUMIFS(ローン返済表!E:E,ローン返済表!B:B,A10) | D10: =SUMIFS(ローン返済表!F:F,ローン返済表!B:B,A10)+SUMIFS(ローン返済表!G:G,ローン返済表!B:B,A10) | E10: =MgmtFee*12 | F10: =ReserveFee*12 | G10: =ParkingFee*12 | H10: =PropertyTax | I10: =FireInsurance | J10: =OtherMaintenance | K10: =IF(A10<=LoanYears,LoanDeduction,0) | L10: =B10+E10+F10+G10+H10+I10+J10-K10 | M10: =M9+L10 | N10: =INDEX(ローン返済表!H:H,A10*12+1)
A11: 9 | B11: =SUMIFS(ローン返済表!D:D,ローン返済表!B:B,A11)+SUMIFS(ローン返済表!G:G,ローン返済表!B:B,A11) | C11: =SUMIFS(ローン返済表!E:E,ローン返済表!B:B,A11) | D11: =SUMIFS(ローン返済表!F:F,ローン返済表!B:B,A11)+SUMIFS(ローン返済表!G:G,ローン返済表!B:B,A11) | E11: =MgmtFee*12 | F11: =ReserveFee*12 | G11: =ParkingFee*12 | H11: =PropertyTax | I11: =FireInsurance | J11: =OtherMaintenance | K11: =IF(A11<=LoanYears,LoanDeduction,0) | L11: =B11+E11+F11+G11+H11+I11+J11-K11 | M11: =M10+L11 | N11: =INDEX(ローン返済表!H:H,A11*12+1)
A12: 10 | B12: =SUMIFS(ローン返済表!D:D,ローン返済表!B:B,A12)+SUMIFS(ローン返済表!G:G,ローン返済表!B:B,A12) | C12: =SUMIFS(ローン返済表!E:E,ローン返済表!B:B,A12) | D12: =SUMIFS(ローン返済表!F:F,ローン返済表!B:B,A12)+SUMIFS(ローン返済表!G:G,ローン返済表!B:B,A12) | E12: =MgmtFee*12 | F12: =ReserveFee*12 | G12: =ParkingFee*12 | H12: =PropertyTax | I12: =FireInsurance | J12: =OtherMaintenance | K12: =IF(A12<=LoanYears,LoanDeduction,0) | L12: =B12+E12+F12+G12+H12+I12+J12-K12 | M12: =M11+L12 | N12: =INDEX(ローン返済表!H:H,A12*12+1)
A13: 11 | B13: =SUMIFS(ローン返済表!D:D,ローン返済表!B:B,A13)+SUMIFS(ローン返済表!G:G,ローン返済表!B:B,A13) | C13: =SUMIFS(ローン返済表!E:E,ローン返済表!B:B,A13) | D13: =SUMIFS(ローン返済表!F:F,ローン返済表!B:B,A13)+SUMIFS(ローン返済表!G:G,ローン返済表!B:B,A13) | E13: =MgmtFee*12 | F13: =ReserveFee*12 | G13: =ParkingFee*12 | H13: =PropertyTax | I13: =FireInsurance | J13: =OtherMaintenance | K13: =IF(A13<=LoanYears,LoanDeduction,0) | L13: =B13+E13+F13+G13+H13+I13+J13-K13 | M13: =M12+L13 | N13: =INDEX(ローン返済表!H:H,A13*12+1)
A14: 12 | B14: =SUMIFS(ローン返済表!D:D,ローン返済表!B:B,A14)+SUMIFS(ローン返済表!G:G,ローン返済表!B:B,A14) | C14: =SUMIFS(ローン返済表!E:E,ローン返済表!B:B,A14) | D14: =SUMIFS(ローン返済表!F:F,ローン返済表!B:B,A14)+SUMIFS(ローン返済表!G:G,ローン返済表!B:B,A14) | E14: =MgmtFee*12 | F14: =ReserveFee*12 | G14: =ParkingFee*12 | H14: =PropertyTax | I14: =FireInsurance | J14: =OtherMaintenance | K14: =IF(A14<=LoanYears,LoanDeduction,0) | L14: =B14+E14+F14+G14+H14+I14+J14-K14 | M14: =M13+L14 | N14: =INDEX(ローン返済表!H:H,A14*12+1)
A15: 13 | B15: =SUMIFS(ローン返済表!D:D,ローン返済表!B:B,A15)+SUMIFS(ローン返済表!G:G,ローン返済表!B:B,A15) | C15: =SUMIFS(ローン返済表!E:E,ローン返済表!B:B,A15) | D15: =SUMIFS(ローン返済表!F:F,ローン返済表!B:B,A15)+SUMIFS(ローン返済表!G:G,ローン返済表!B:B,A15) | E15: =MgmtFee*12 | F15: =ReserveFee*12 | G15: =ParkingFee*12 | H15: =PropertyTax | I15: =FireInsurance | J15: =OtherMaintenance | K15: =IF(A15<=LoanYears,LoanDeduction,0) | L15: =B15+E15+F15+G15+H15+I15+J15-K15 | M15: =M14+L15 | N15: =INDEX(ローン返済表!H:H,A15*12+1)
... A37: 35 | B37: =SUMIFS(ローン返済表!D:D,ローン返済表!B:B,A37)+SUMIFS(ローン返済表!G:G,ローン返済表!B:B,A37) | C37: =SUMIFS(ローン返済表!E:E,ローン返済表!B:B,A37) | D37: =SUMIFS(ローン返済表!F:F,ローン返済表!B:B,A37)+SUMIFS(ローン返済表!G:G,ローン返済表!B:B,A37) | E37: =MgmtFee*12 | F37: =ReserveFee*12 | G37: =ParkingFee*12 | H37: =PropertyTax | I37: =FireInsurance | J37: =OtherMaintenance | K37: =IF(A37<=LoanYears,LoanDeduction,0) | L37: =B37+E37+F37+G37+H37+I37+J37-K37 | M37: =M36+L37 | N37: =INDEX(ローン返済表!H:H,A37*12+1)

Sheet 売却精算
A1: 売却精算（保有年数後に売却した場合）
A2: 項目 | B2: 金額 | C2: 説明
A3: 売却価格 | B3: =SalePrice | C3: 前提入力シートの売却予定価格
A4: 売却時仲介手数料 | B4: =SalePrice*SaleFeeRate | C4: 売却価格×売却時仲介手数料率
A5: 売却時その他費用 | B5: =SaleOtherCost | C5: 抵当権抹消・登記等の費用
A6: 売却時ローン残債 | B6: =INDEX(ローン返済表!H:H,HoldYears*12+1) | C6: 保有年数×12か月時点のローン残高（ローン返済表より参照）
A7: 売却後手残り | B7: =B3-B4-B5-B6 | C7: 売却価格-仲介手数料-その他費用-ローン残債
A8: 売却損益の参考値 | B8: =SalePrice-Price | C8: 売却価格-購入時の物件価格（簡易参考値。税金等は考慮せず）

Sheet 実質家賃結果
A1: 実質家賃結果（最終まとめ）
A2: 項目 | B2: 値 | C2: 説明
A3: 購入時支出 | B3: =DownPayment+PurchaseCost | C3: 頭金+購入時諸費用
A4: 保有期間中の総支出 | B4: =SUMIFS(年次集計!L:L,年次集計!A:A,"<="&HoldYears) | C4: 保有年数までの年間実質支出（ローン返済・維持費-控除）の合計
A5: 売却後手残り | B5: =売却精算!B7 | C5: 売却精算シートより参照
A6: 引越し費用 | B6: =MovingCost | C6: 前提入力シートより参照
A7: 実質負担額 | B7: =B3+B4-B5+B6 | C7: 購入時支出+保有期間中の総支出-売却後手残り+引越し費用
A8: 保有月数 | B8: =HoldYears*12 | C8: 保有年数×12
A9: 実質月額家賃 | B9: =B7/B8 | C9: 実質負担額÷保有月数
A10: 賃貸継続時の総支出 | B10: =CurrentRent*B8 | C10: 現在家賃×保有月数
A11: 賃貸との差額 | B11: =B7-B10 | C11: 実質負担額-賃貸継続時の総支出（マイナスなら購入の方が有利）

Sheet シナリオ比較
A1: シナリオ比較（保有年数×売却価格 → 実質月額家賃）
A2: ※ このシートは比較のための簡易計算です。ボーナス返済は考慮せず、通常の元利均等返済（PMT）の計算式のみで残高・支払額を再計算しています。
A4: 保有年数 ＼ 売却価格（購入価格に対する比率） | B4: 0.7 | C4: 0.8 | D4: 0.9 | E4: 1 | F4: 1.1
A5: 3 | B5: =(F14-Price*B$4*(1-SaleFeeRate))/(A5*12) | C5: =(F14-Price*C$4*(1-SaleFeeRate))/(A5*12) | D5: =(F14-Price*D$4*(1-SaleFeeRate))/(A5*12) | E5: =(F14-Price*E$4*(1-SaleFeeRate))/(A5*12) | F5: =(F14-Price*F$4*(1-SaleFeeRate))/(A5*12)
A6: 5 | B6: =(F15-Price*B$4*(1-SaleFeeRate))/(A6*12) | C6: =(F15-Price*C$4*(1-SaleFeeRate))/(A6*12) | D6: =(F15-Price*D$4*(1-SaleFeeRate))/(A6*12) | E6: =(F15-Price*E$4*(1-SaleFeeRate))/(A6*12) | F6: =(F15-Price*F$4*(1-SaleFeeRate))/(A6*12)
A7: 7 | B7: =(F16-Price*B$4*(1-SaleFeeRate))/(A7*12) | C7: =(F16-Price*C$4*(1-SaleFeeRate))/(A7*12) | D7: =(F16-Price*D$4*(1-SaleFeeRate))/(A7*12) | E7: =(F16-Price*E$4*(1-SaleFeeRate))/(A7*12) | F7: =(F16-Price*F$4*(1-SaleFeeRate))/(A7*12)
A8: 10 | B8: =(F17-Price*B$4*(1-SaleFeeRate))/(A8*12) | C8: =(F17-Price*C$4*(1-SaleFeeRate))/(A8*12) | D8: =(F17-Price*D$4*(1-SaleFeeRate))/(A8*12) | E8: =(F17-Price*E$4*(1-SaleFeeRate))/(A8*12) | F8: =(F17-Price*F$4*(1-SaleFeeRate))/(A8*12)
A9: 15 | B9: =(F18-Price*B$4*(1-SaleFeeRate))/(A9*12) | C9: =(F18-Price*C$4*(1-SaleFeeRate))/(A9*12) | D9: =(F18-Price*D$4*(1-SaleFeeRate))/(A9*12) | E9: =(F18-Price*E$4*(1-SaleFeeRate))/(A9*12) | F9: =(F18-Price*F$4*(1-SaleFeeRate))/(A9*12)
A12: 【内部計算用ヘルパー表（保有年数ごとの固定部分）】
A13: 保有年数 | B13: 月額返済(M) | C13: 保有月数(n) | D13: 想定残高(Balance) | E13: 保有総支出 | F13: fixed_part
A14: =A5 | B14: =-PMT(InterestRate/12,LoanYears*12,LoanAmount) | C14: =A14*12 | D14: =LoanAmount*(1+InterestRate/12)^C14-B14*((1+InterestRate/12)^C14-1)/(InterestRate/12) | E14: =B14*C14+((MgmtFee+ReserveFee+ParkingFee)*12+PropertyTax+FireInsurance+OtherMaintenance)*A14-LoanDeduction*MIN(A14,LoanYears) | F14: =(DownPayment+PurchaseCost)+E14+SaleOtherCost+D14+MovingCost
A15: =A6 | B15: =-PMT(InterestRate/12,LoanYears*12,LoanAmount) | C15: =A15*12 | D15: =LoanAmount*(1+InterestRate/12)^C15-B15*((1+InterestRate/12)^C15-1)/(InterestRate/12) | E15: =B15*C15+((MgmtFee+ReserveFee+ParkingFee)*12+PropertyTax+FireInsurance+OtherMaintenance)*A15-LoanDeduction*MIN(A15,LoanYears) | F15: =(DownPayment+PurchaseCost)+E15+SaleOtherCost+D15+MovingCost
A16: =A7 | B16: =-PMT(InterestRate/12,LoanYears*12,LoanAmount) | C16: =A16*12 | D16: =LoanAmount*(1+InterestRate/12)^C16-B16*((1+InterestRate/12)^C16-1)/(InterestRate/12) | E16: =B16*C16+((MgmtFee+ReserveFee+ParkingFee)*12+PropertyTax+FireInsurance+OtherMaintenance)*A16-LoanDeduction*MIN(A16,LoanYears) | F16: =(DownPayment+PurchaseCost)+E16+SaleOtherCost+D16+MovingCost
A17: =A8 | B17: =-PMT(InterestRate/12,LoanYears*12,LoanAmount) | C17: =A17*12 | D17: =LoanAmount*(1+InterestRate/12)^C17-B17*((1+InterestRate/12)^C17-1)/(InterestRate/12) | E17: =B17*C17+((MgmtFee+ReserveFee+ParkingFee)*12+PropertyTax+FireInsurance+OtherMaintenance)*A17-LoanDeduction*MIN(A17,LoanYears) | F17: =(DownPayment+PurchaseCost)+E17+SaleOtherCost+D17+MovingCost
A18: =A9 | B18: =-PMT(InterestRate/12,LoanYears*12,LoanAmount) | C18: =A18*12 | D18: =LoanAmount*(1+InterestRate/12)^C18-B18*((1+InterestRate/12)^C18-1)/(InterestRate/12) | E18: =B18*C18+((MgmtFee+ReserveFee+ParkingFee)*12+PropertyTax+FireInsurance+OtherMaintenance)*A18-LoanDeduction*MIN(A18,LoanYears) | F18: =(DownPayment+PurchaseCost)+E18+SaleOtherCost+D18+MovingCost
